minutes/__init__.py
minutes/admin.py
minutes/apps.py
minutes/signals.py
minutes/urls.py
minutes/views.py
minutes/api/__init__.py
minutes/api/urls.py
minutes/api/common/__init__.py
minutes/api/common/serializers/__init__.py
minutes/api/common/serializers/author.py
minutes/api/common/serializers/edition.py
minutes/api/common/serializers/interstitial_instance.py
minutes/api/common/serializers/minute.py
minutes/api/common/serializers/native_ad.py
minutes/api/common/serializers/sponsor.py
minutes/api/common/serializers/vertical.py
minutes/api/common/viewsets/__init__.py
minutes/api/common/viewsets/base.py
minutes/api/edition/__init__.py
minutes/api/edition/viewset.py
minutes/api/vertical/__init__.py
minutes/api/vertical/viewset.py
minutes/cms/__init__.py
minutes/cms/urls.py
minutes/cms/business/__init__.py
minutes/cms/business/views/__init__.py
minutes/cms/business/views/business.py
minutes/cms/common/__init__.py
minutes/cms/common/serializers/__init__.py
minutes/cms/common/serializers/editing_session.py
minutes/cms/common/serializers/interstitial.py
minutes/cms/common/serializers/interstitial_type.py
minutes/cms/common/serializers/minute_type.py
minutes/cms/common/serializers/native_ad.py
minutes/cms/common/serializers/sponsor.py
minutes/cms/common/serializers/theme.py
minutes/cms/common/serializers/user.py
minutes/cms/common/serializers/vertical.py
minutes/cms/common/views/__init__.py
minutes/cms/common/views/base.py
minutes/cms/common/viewsets/__init__.py
minutes/cms/common/viewsets/base.py
minutes/cms/common/viewsets/editing_session.py
minutes/cms/edition/__init__.py
minutes/cms/edition/viewset.py
minutes/cms/edition/serializers/__init__.py
minutes/cms/edition/serializers/edition.py
minutes/cms/edition/serializers/interstitial_instance.py
minutes/cms/edition/serializers/minute.py
minutes/cms/edition/serializers/minute_type.py
minutes/cms/edition/views/__init__.py
minutes/cms/edition/views/edition.py
minutes/cms/home/__init__.py
minutes/cms/home/views/__init__.py
django_politico_minutes_editor-1.1.1.dist-info/LICENSE
django_politico_minutes_editor-1.1.1.dist-info/METADATA
django_politico_minutes_editor-1.1.1.dist-info/WHEEL
django_politico_minutes_editor-1.1.1.dist-info/top_level.txt
django_politico_minutes_editor-1.1.1.dist-info/RECORD
